kz/__init__.py
kz-0.dev1.dist-info/DESCRIPTION.rst
kz-0.dev1.dist-info/METADATA
kz-0.dev1.dist-info/RECORD
kz-0.dev1.dist-info/WHEEL
kz-0.dev1.dist-info/metadata.json
kz-0.dev1.dist-info/top_level.txt
tests/__init__.py
tests/test_sample.py
